{"chunk_definitions":[{"row":33,"row_count":1,"visible":true,"expansion_state":0,"options":{"engine":"r","label":"unnamed-chunk-3","dev":"png"},"document_id":"85ADBAB1","chunk_id":"c0xetrwq5svp5","chunk_label":"unnamed-chunk-1"},{"row":43,"row_count":1,"visible":true,"expansion_state":0,"options":{"engine":"r","label":"unnamed-chunk-4","dev":"png"},"document_id":"85ADBAB1","chunk_id":"c9d9qgpcodrx6","chunk_label":"unnamed-chunk-2"},{"row":47,"row_count":1,"visible":true,"expansion_state":0,"options":{"engine":"r","echo":false,"label":"unnamed-chunk-5","dev":"png"},"document_id":"85ADBAB1","chunk_id":"cb7z154eg68bo","chunk_label":"unnamed-chunk-3"},{"row":61,"row_count":1,"visible":true,"expansion_state":0,"options":{"engine":"r","label":"unnamed-chunk-6","dev":"png"},"document_id":"85ADBAB1","chunk_id":"cap25rvhqdqts","chunk_label":"unnamed-chunk-4"},{"row":85,"row_count":1,"visible":true,"expansion_state":0,"options":{"engine":"r","eval":false,"label":"unnamed-chunk-5","dev":"png"},"document_id":"85ADBAB1","chunk_id":"ceynbysjd0woj","chunk_label":"unnamed-chunk-5"},{"row":104,"row_count":1,"visible":true,"expansion_state":0,"options":{"engine":"r","label":"unnamed-chunk-7","dev":"png"},"document_id":"85ADBAB1","chunk_id":"c2x3k93y5whpb","chunk_label":"unnamed-chunk-6"},{"row":108,"row_count":1,"visible":true,"expansion_state":0,"options":{"engine":"r","label":"unnamed-chunk-8","dev":"png"},"document_id":"85ADBAB1","chunk_id":"cs21vbetu6yl7","chunk_label":"unnamed-chunk-7"},{"row":156,"row_count":1,"visible":true,"expansion_state":0,"options":{"engine":"r","eval":false,"label":"unnamed-chunk-1","dev":"png"},"document_id":"85ADBAB1","chunk_id":"c8bx04mamh764","chunk_label":"unnamed-chunk-8"},{"row":161,"row_count":1,"visible":true,"expansion_state":0,"options":{"engine":"r","label":"unnamed-chunk-9","dev":"png"},"document_id":"85ADBAB1","chunk_id":"crih76b0gwspf","chunk_label":"unnamed-chunk-9"},{"row":170,"row_count":1,"visible":true,"expansion_state":0,"options":{"engine":"r","label":"unnamed-chunk-10","dev":"png"},"document_id":"85ADBAB1","chunk_id":"crt6dblp2xe0y","chunk_label":"unnamed-chunk-10"},{"row":198,"row_count":1,"visible":true,"expansion_state":0,"options":{"engine":"r","label":"unnamed-chunk-69","dev":"png"},"document_id":"85ADBAB1","chunk_id":"cau6wdg3lhp6y","chunk_label":"unnamed-chunk-11"},{"row":206,"row_count":1,"visible":true,"expansion_state":0,"options":{"engine":"r","label":"unnamed-chunk-70","dev":"png"},"document_id":"85ADBAB1","chunk_id":"c5oaqx7h6piaf","chunk_label":"unnamed-chunk-12"},{"row":214,"row_count":1,"visible":true,"expansion_state":0,"options":{"engine":"r","label":"unnamed-chunk-83","dev":"png"},"document_id":"85ADBAB1","chunk_id":"c9gvxlcboojzu","chunk_label":"unnamed-chunk-13"}],"doc_write_time":1709695305}